gecosistema_learning/LSTM.py
gecosistema_learning/SVRM.py
gecosistema_learning/__init__.py
gecosistema_learning/machine_learning.py
gecosistema_learning-0.0.43.dist-info/METADATA
gecosistema_learning-0.0.43.dist-info/RECORD
gecosistema_learning-0.0.43.dist-info/WHEEL
gecosistema_learning-0.0.43.dist-info/top_level.txt
